dcacheclient/__init__.py
dcacheclient/client.py
dcacheclient/dcache_admin.2.py
dcacheclient/dcache_admin.py
dcacheclient/api/__init__.py
dcacheclient/api/v1/__init__.py
dcacheclient/api/v1/alarms.py
dcacheclient/api/v1/billing.py
dcacheclient/api/v1/cells.py
dcacheclient/api/v1/events.py
dcacheclient/api/v1/identity.py
dcacheclient/api/v1/namespace.py
dcacheclient/api/v1/poolmanager.py
dcacheclient/api/v1/pools.py
dcacheclient/api/v1/qos.py
dcacheclient/api/v1/spacemanager.py
dcacheclient/api/v1/transfers.py
dcacheclient/common/__init__.py
dcacheclient/common/utils.py
dcacheclient/sync/__init__.py
dcacheclient/sync/panoptes.py
dcacheclient-0.0.5.dist-info/LICENSE
dcacheclient-0.0.5.dist-info/METADATA
dcacheclient-0.0.5.dist-info/WHEEL
dcacheclient-0.0.5.dist-info/entry_points.txt
dcacheclient-0.0.5.dist-info/top_level.txt
dcacheclient-0.0.5.dist-info/RECORD
