Metadata-Version: 2.1
Name: dcacheclient
Version: 0.0.5
Summary: UNKNOWN
Home-page: https://www.dcache.org
Author: UNKNOWN
Author-email: support@dCache.org
License: UNKNOWN
Keywords: dCache,storage
Platform: UNKNOWN
Requires-Dist: six (>=1.10)
Requires-Dist: requests (>=2.6.0)
Requires-Dist: urllib3 (<1.25,>=1.21.1)
Requires-Dist: certifi
Requires-Dist: python-dateutil
Requires-Dist: argcomplete (>=1.9.4)
Requires-Dist: sseclient
